{"nodes": [{"id": "lib_hibp_ts", "label": "hibp.ts", "file_type": "code", "source_file": "lib/hibp.ts", "source_location": "L1"}, {"id": "hibp_sha1hex", "label": "sha1Hex()", "file_type": "code", "source_file": "lib/hibp.ts", "source_location": "L18"}, {"id": "hibp_checkpassword", "label": "checkPassword()", "file_type": "code", "source_file": "lib/hibp.ts", "source_location": "L27"}], "edges": [{"source": "lib_hibp_ts", "target": "hibp_sha1hex", "relation": "contains", "confidence": "EXTRACTED", "source_file": "lib/hibp.ts", "source_location": "L18", "weight": 1.0}, {"source": "lib_hibp_ts", "target": "hibp_checkpassword", "relation": "contains", "confidence": "EXTRACTED", "source_file": "lib/hibp.ts", "source_location": "L27", "weight": 1.0}, {"source": "hibp_checkpassword", "target": "hibp_sha1hex", "relation": "calls", "confidence": "EXTRACTED", "source_file": "lib/hibp.ts", "source_location": "L31", "weight": 1.0}], "raw_calls": [{"caller_nid": "hibp_sha1hex", "callee": "encode", "source_file": "lib/hibp.ts", "source_location": "L19"}, {"caller_nid": "hibp_sha1hex", "callee": "digest", "source_file": "lib/hibp.ts", "source_location": "L20"}, {"caller_nid": "hibp_sha1hex", "callee": "toUpperCase", "source_file": "lib/hibp.ts", "source_location": "L21"}, {"caller_nid": "hibp_sha1hex", "callee": "join", "source_file": "lib/hibp.ts", "source_location": "L21"}, {"caller_nid": "hibp_sha1hex", "callee": "map", "source_file": "lib/hibp.ts", "source_location": "L21"}, {"caller_nid": "hibp_sha1hex", "callee": "from", "source_file": "lib/hibp.ts", "source_location": "L21"}, {"caller_nid": "hibp_checkpassword", "callee": "slice", "source_file": "lib/hibp.ts", "source_location": "L35"}, {"caller_nid": "hibp_checkpassword", "callee": "slice", "source_file": "lib/hibp.ts", "source_location": "L36"}, {"caller_nid": "hibp_checkpassword", "callee": "fetch", "source_file": "lib/hibp.ts", "source_location": "L39"}, {"caller_nid": "hibp_checkpassword", "callee": "text", "source_file": "lib/hibp.ts", "source_location": "L44"}, {"caller_nid": "hibp_checkpassword", "callee": "split", "source_file": "lib/hibp.ts", "source_location": "L45"}, {"caller_nid": "hibp_checkpassword", "callee": "split", "source_file": "lib/hibp.ts", "source_location": "L46"}, {"caller_nid": "hibp_checkpassword", "callee": "trim", "source_file": "lib/hibp.ts", "source_location": "L46"}, {"caller_nid": "hibp_checkpassword", "callee": "parseInt", "source_file": "lib/hibp.ts", "source_location": "L48"}]}